argparse_env/__init__.py
argparse_env/envparser.py
argparse_env-0.1.2.dist-info/METADATA
argparse_env-0.1.2.dist-info/WHEEL
argparse_env-0.1.2.dist-info/top_level.txt
argparse_env-0.1.2.dist-info/RECORD
