Metadata-Version: 2.4
Name: argparse-env
Version: 0.1.2
Summary: An argpase that can take values from the environment.
Requires-Python: >=3.9
